upt_guix/__init__.py
upt_guix/upt_guix.py
upt_guix/tests/__init__.py
upt_guix/tests/test_cpan_package.py
upt_guix/tests/test_guix_backend.py
upt_guix/tests/test_guix_package.py
upt_guix/tests/test_pypi_package.py
upt_guix/tests/test_rubygems_package.py
upt_guix-0.2.dist-info/DESCRIPTION.rst
upt_guix-0.2.dist-info/METADATA
upt_guix-0.2.dist-info/RECORD
upt_guix-0.2.dist-info/WHEEL
upt_guix-0.2.dist-info/entry_points.txt
upt_guix-0.2.dist-info/metadata.json
upt_guix-0.2.dist-info/top_level.txt
