Metadata-Version: 2.0
Name: upt-guix
Version: 0.2
Summary: GNU Guix backend for upt
Home-page: https://framagit.org/upt/upt-guix
Author: Cyril Roelandt
Author-email: tipecaml@gmail.com
License: UNKNOWN
Platform: UNKNOWN
Classifier: Development Status :: 3 - Alpha
Classifier: License :: OSI Approved :: BSD License
Classifier: Programming Language :: Python :: 3
Classifier: Programming Language :: Python :: 3.6
Requires-Dist: upt (>=0.2)
